__init__.py
table15/__init__.py
table15/__main__.py
table15/configs.py
table15/runner.py
table15/models/__init__.py
table15/models/deep_models.py
table15/models/ensemble_models.py
table15/models/linear_models.py
table15/models/model.py
table15/models/model_factory.py
table15/models/svm_models.py
table15/models/test_linear_model.py
table15/perturbations/__init__.py
table15/perturbations/group_perturbation.py
table15/perturbations/perturbation.py
table15/perturbations/z_perturbation.py
table15/utils/__init__.py
table15/utils/data_tables.py
table15/utils/magec_utils.py
table15/utils/models_container.py
table15/utils/pipeline_utils.py
table15-1.0.1.dist-info/LICENSE
table15-1.0.1.dist-info/METADATA
table15-1.0.1.dist-info/WHEEL
table15-1.0.1.dist-info/entry_points.txt
table15-1.0.1.dist-info/top_level.txt
table15-1.0.1.dist-info/RECORD
