Metadata-Version: 2.1
Name: table15
Version: 1.0.1
Summary: Table 1.5 is a Python application that can generate a table that is adjunct to a typical Table 1 (association statistics). Table 1.5 goes beyond static association by analyzing the impact that a change in each single feature has to changes in the outcome.
Author-email: Rajas Kale <rajas.kale@carelon.com>
License: The MIT License (MIT)
Project-URL: Homepage, https://https://github.com/KaleRP/table15
Keywords: Table1.5
Classifier: License :: OSI Approved :: MIT License
Classifier: Programming Language :: Python
Classifier: Programming Language :: Python :: 3
Requires-Python: >=3.7
License-File: LICENSE
Requires-Dist: pandas (>=0.25)
Requires-Dist: scikit-learn (>=1.1.2)
Requires-Dist: keras (>=2.10.0)
Requires-Dist: scikeras (>=0.9.0)
Requires-Dist: numpy (>=1.23.3)
Requires-Dist: shap (>=0.41.0)
Requires-Dist: PyYAML (>=6.0)
